LICENSE.txt
README.md
setup.cfg
setup.py
pynumsys/__init__.py
pynumsys/binary.py
pynumsys/comp.py
pynumsys/decimal.py
pynumsys/hexadecimal.py
pynumsys/octal.py
pynumsys.egg-info/PKG-INFO
pynumsys.egg-info/SOURCES.txt
pynumsys.egg-info/dependency_links.txt
pynumsys.egg-info/top_level.txt