Metadata-Version: 2.1
Name: pynumsys
Version: 0.1
Summary: Python package to convert one number system to another such as binary to decimal, decimal to binary, hexadecimal to octal, octal to hexadecimal etc...
Home-page: https://github.com/roshaan555/pynumsys
Download-URL: https://github.com/roshaan555/pynumsys/releases/download/v_0.1/pynumsys-0.1.tar.gz
Author: Roshaan Mehmood
Author-email: roshaan55@gmail.com
License: MIT
Keywords: pynumsys,numbersystem,octal to hexadecimal,binary to octal,binary,decimal
Classifier: Development Status :: 3 - Alpha
Classifier: Intended Audience :: Developers
Classifier: Topic :: Software Development :: Build Tools
Classifier: License :: OSI Approved :: MIT License
Classifier: Programming Language :: Python :: 3.6
Classifier: Programming Language :: Python :: 3.7
Classifier: Programming Language :: Python :: 3.8
Classifier: Programming Language :: Python :: 3.9
Classifier: Programming Language :: Python :: 3.10
Classifier: Programming Language :: Python :: 3.11
Classifier: Programming Language :: Python :: 3.12
License-File: LICENSE.txt
